nichey/__init__.py
nichey/db.py
nichey/exceptions.py
nichey/file_loaders.py
nichey/lm.py
nichey/logger.py
nichey/scraper.py
nichey/search_engine.py
nichey/utils.py
nichey/wiki.py
nichey/static/404.html
nichey/static/500.html
nichey/static/CloseIcon.png
nichey/static/DeleteIcon.png
nichey/static/EditIcon.png
nichey/static/article.html
nichey/static/articles.html
nichey/static/index.html
nichey/static/source.html
nichey/static/sources.html
nichey/static/_next/static/chunks/9-cf74b2a6aa463331.js
nichey/static/_next/static/chunks/framework-a4ddb9b21624b39b.js
nichey/static/_next/static/chunks/main-e5cda668ab60045f.js
nichey/static/_next/static/chunks/polyfills-42372ed130431b0a.js
nichey/static/_next/static/chunks/webpack-6ffd07a3317375c1.js
nichey/static/_next/static/chunks/pages/404-a3bc5648629410d5.js
nichey/static/_next/static/chunks/pages/500-079d29db5bc05d18.js
nichey/static/_next/static/chunks/pages/_app-14caa6293799d4e8.js
nichey/static/_next/static/chunks/pages/_error-fde50cb7f1ab27e0.js
nichey/static/_next/static/chunks/pages/article-47973af8c72f6d61.js
nichey/static/_next/static/chunks/pages/articles-8cd425037154f5a6.js
nichey/static/_next/static/chunks/pages/index-c5b4576aaa6e321d.js
nichey/static/_next/static/chunks/pages/source-5d3aabad73965638.js
nichey/static/_next/static/chunks/pages/sources-9bb7e675cd88cc75.js
nichey/static/_next/static/css/56760f2dc2513ffb.css
nichey/static/_next/static/css/7664c1449da0a98b.css
nichey/static/_next/static/l0RQPpRE2gztOI9aLqcp3/_buildManifest.js
nichey/static/_next/static/l0RQPpRE2gztOI9aLqcp3/_ssgManifest.js
nichey/static/_next/static/media/CloseIcon.8995a7c5.png
nichey/static/_next/static/media/DeleteIcon.f2407bd6.png
nichey/static/_next/static/media/EditIcon.8f1ff925.png
nichey-0.1.1.dist-info/LICENSE
nichey-0.1.1.dist-info/METADATA
nichey-0.1.1.dist-info/WHEEL
nichey-0.1.1.dist-info/top_level.txt
nichey-0.1.1.dist-info/RECORD
