Metadata-Version: 2.2
Name: nichey
Version: 0.1.1
Summary: Build a wiki for your research topic
Home-page: https://github.com/goodreasonai/nichey
Author: Gordon Kamer
Author-email: gordon@goodreason.ai
Classifier: Programming Language :: Python :: 3
Classifier: License :: OSI Approved :: MIT License
Classifier: Operating System :: OS Independent
Requires-Python: >=3.7
License-File: LICENSE
Requires-Dist: requests
Requires-Dist: openai
Requires-Dist: pydantic
Requires-Dist: beautifulsoup4
Requires-Dist: requests-toolbelt
Requires-Dist: unstructured[csv,doc,docx,epub,md,msg,odt,org,ppt,pptx,rst,rtf,tsv,xlsx]
Requires-Dist: pymupdf
Requires-Dist: tiktoken
Requires-Dist: python-slugify
Requires-Dist: flask
Requires-Dist: flask_cors
Requires-Dist: tqdm
Dynamic: author
Dynamic: author-email
Dynamic: classifier
Dynamic: description
Dynamic: description-content-type
Dynamic: home-page
Dynamic: requires-dist
Dynamic: requires-python
Dynamic: summary
